nice/__init__.py
nice/utils/__init__.py
nice/utils/data.py
nice/utils/distance.py
nice/utils/preprocessing.py
nice/utils/optimization/__init__.py
nice/utils/optimization/heuristic.py
nice/utils/optimization/reward.py
NICEx-0.2.3.dist-info/LICENSE.txt
NICEx-0.2.3.dist-info/METADATA
NICEx-0.2.3.dist-info/WHEEL
NICEx-0.2.3.dist-info/top_level.txt
NICEx-0.2.3.dist-info/RECORD
