Metadata-Version: 2.1
Name: NICEx
Version: 0.2.3
Summary: Nearest Instance Counterfactual explanations
Home-page: https://github.com/DBrughmans/NICE
Author: Dieter Brughmans
Author-email: dieter.brughmans@uantwerpen.be
License: Apache 2.0
Keywords: Counterfactual Explanations XAI
Platform: UNKNOWN
Classifier: Development Status :: 2 - Pre-Alpha
Classifier: Programming Language :: Python :: 3
Requires-Python: >=3.6
License-File: LICENSE.txt
Requires-Dist: numpy (<2.0.0,>=1.16.2)
Requires-Dist: pandas (<2.0.0,>=0.23.3)
